{"metadata": {"timestamp": 1706937283.536206, "commit_hash": "b6c5b2401c168a6123d6789f3b3749ced390a2d4", "used_seed_indexes": [0], "used_seeds": [301797735]}, "team_sets": [{"_id": "954f959f-c929-46b1-9dd1-9618f21eae55--run_index_0--seed_301797735", "name": null, "teams": [{"_id": 1, "name": "Team 1", "project_id": null, "requirements": [], "students": [{"_id": 61989, "name": "Stephen Garrett", "attributes": {"1": [1], "7": [5], "6": [3], "100": [3]}, "relationships": {"23276": -1, "-1": -1, "35506": 1.1}, "project_preferences": []}, {"_id": 21490, "name": "Lori Brown", "attributes": {"1": [1], "7": [3, 4, 5], "6": [3], "100": [4]}, "relationships": {"38756": -1, "-1": 1.1}, "project_preferences": []}, {"_id": 52400, "name": "Jacob Grant", "attributes": {"1": [1], "7": [3, 4, 5], "6": [3], "100": [3]}, "relationships": {"68546": -1, "19276": -1, "53713": -1, "-1": 1.1}, "project_preferences": []}, {"_id": 46440, "name": "Jordan Price", "attributes": {"1": [1], "7": [3, 4, 5, 6], "6": [3], "100": [3]}, "relationships": {"44120": -1, "62437": -1, "63773": -1, "65317": 1.1}, "project_preferences": []}]}, {"_id": 2, "name": "Team 2", "project_id": null, "requirements": [], "students": [{"_id": 45335, "name": "Kristy Mckenzie", "attributes": {"1": [2], "7": [2, 3], "6": [3], "100": [4]}, "relationships": {"85891": -1, "16024": -1, "55265": -1, "21965": 1.1}, "project_preferences": []}, {"_id": 79814, "name": "Mr. Kyle Brown", "attributes": {"1": [2], "7": [1, 2, 4, 5, 6], "6": [3], "100": [3]}, "relationships": {"29846": -1, "85726": -1, "22172": -1, "-1": 1.1}, "project_preferences": []}, {"_id": 21965, "name": "Bailey Howard", "attributes": {"1": [1], "7": [2, 5], "6": [3], "100": [3]}, "relationships": {"55265": -1, "28996": -1, "24996": -1, "21965": 1.1}, "project_preferences": []}, {"_id": 81962, "name": "Timothy Williams", "attributes": {"1": [2], "7": [2, 3, 4, 5], "6": [3], "100": [3]}, "relationships": {"53746": -1, "-1": 1.1}, "project_preferences": []}]}, {"_id": 3, "name": "Team 3", "project_id": null, "requirements": [], "students": [{"_id": 52521, "name": "Joseph Carpenter", "attributes": {"1": [2], "7": [4, 5], "6": [3], "100": [4]}, "relationships": {"61306": -1, "37147": -1, "-1": 1.1}, "project_preferences": []}, {"_id": 56201, "name": "Julia Kemp", "attributes": {"1": [2], "7": [5, 6], "6": [3], "100": [4]}, "relationships": {"-1": 1.1}, "project_preferences": []}, {"_id": 36880, "name": "Felicia Kelley", "attributes": {"1": [2], "7": [2, 5, 6], "6": [3], "100": [3]}, "relationships": {"65204": -1, "57350": -1, "-1": 1.1}, "project_preferences": []}, {"_id": 51805, "name": "Elizabeth Black", "attributes": {"1": [2], "7": [1, 4, 5], "6": [3], "100": [4]}, "relationships": {"49915": -1, "99819": -1, "32896": -1, "35506": 1.1}, "project_preferences": []}]}, {"_id": 4, "name": "Team 4", "project_id": null, "requirements": [], "students": [{"_id": 87008, "name": "Amanda Parker", "attributes": {"1": [2], "7": [3, 4, 5], "6": [3], "100": [3]}, "relationships": {"20288": -1, "19992": -1, "52400": -1, "42656": 1.1}, "project_preferences": []}, {"_id": 73471, "name": "Derek Henderson", "attributes": {"1": [2], "7": [3, 4, 5], "6": [3], "100": [3]}, "relationships": {"-1": 1.1}, "project_preferences": []}, {"_id": 21484, "name": "Victor Davis", "attributes": {"1": [2], "7": [2, 3, 4, 5], "6": [3], "100": [3]}, "relationships": {"-1": -1, "21001": 1.1}, "project_preferences": []}, {"_id": 53713, "name": "Dylan Perry", "attributes": {"1": [1], "7": [2, 3, 4, 5, 6], "6": [3], "100": [4]}, "relationships": {"-1": 1.1}, "project_preferences": []}]}, {"_id": 5, "name": "Team 5", "project_id": null, "requirements": [], "students": [{"_id": 59964, "name": "Matthew Lee", "attributes": {"1": [1], "7": [3, 4, 5], "6": [3], "100": [3]}, "relationships": {"-1": 1.1}, "project_preferences": []}, {"_id": 45301, "name": "Robert Contreras", "attributes": {"1": [1], "7": [2, 3, 4, 5], "6": [3], "100": [3]}, "relationships": {"30296": -1, "30600": -1, "38069": -1, "-1": 1.1}, "project_preferences": []}, {"_id": 84048, "name": "Belinda Campbell", "attributes": {"1": [1], "7": [3, 4, 5, 6], "6": [3], "100": [3]}, "relationships": {"-1": 1.1}, "project_preferences": []}, {"_id": 92817, "name": "Robert White", "attributes": {"1": [1], "7": [3, 4, 5, 6], "6": [3], "100": [3]}, "relationships": {"44120": -1, "85726": -1, "80449": -1, "18267": 1.1}, "project_preferences": []}]}, {"_id": 6, "name": "Team 6", "project_id": null, "requirements": [], "students": [{"_id": 15382, "name": "Roberto Pace", "attributes": {"1": [1], "7": [1, 2, 3, 4, 5, 6], "6": [3], "100": [3]}, "relationships": {"-1": -1, "71974": 1.1}, "project_preferences": []}, {"_id": 22172, "name": "Brandon Mcknight", "attributes": {"1": [1], "7": [2, 3, 4, 5, 6], "6": [3], "100": [3]}, "relationships": {"29846": -1, "79814": -1, "85726": -1, "-1": 1.1}, "project_preferences": []}, {"_id": 75087, "name": "Jose Barnes", "attributes": {"1": [1], "7": [5, 6], "6": [3], "100": [4]}, "relationships": {"19992": -1, "-1": -1, "21965": 1.1}, "project_preferences": []}, {"_id": 77507, "name": "Danielle Rhodes", "attributes": {"1": [1], "7": [1, 2, 3, 4, 5, 6], "6": [3], "100": [4]}, "relationships": {"-1": 1.1}, "project_preferences": []}]}, {"_id": 7, "name": "Team 7", "project_id": null, "requirements": [], "students": [{"_id": 98435, "name": "David Mcbride", "attributes": {"1": [3], "7": [4], "6": [3], "100": [4]}, "relationships": {"61306": -1, "99819": -1, "37147": -1, "24907": 1.1}, "project_preferences": []}, {"_id": 55362, "name": "Joshua Velazquez", "attributes": {"1": [3], "7": [3, 4, 6], "6": [3], "100": [3]}, "relationships": {"52521": -1, "-1": 1.1}, "project_preferences": []}, {"_id": 69525, "name": "Michelle Edwards", "attributes": {"1": [1], "7": [5, 6], "6": [3], "100": [3]}, "relationships": {"-1": 1.1}, "project_preferences": []}, {"_id": 19872, "name": "William Ross", "attributes": {"1": [2], "7": [5, 6], "6": [3], "100": [3]}, "relationships": {"-1": 1.1}, "project_preferences": []}]}, {"_id": 8, "name": "Team 8", "project_id": null, "requirements": [], "students": [{"_id": 10223, "name": "William Kelley", "attributes": {"1": [1], "7": [3, 4, 5], "6": [3], "100": [3]}, "relationships": {"-1": 1.1}, "project_preferences": []}, {"_id": 18267, "name": "Seth Wright", "attributes": {"1": [1], "7": [3], "6": [3], "100": [4]}, "relationships": {"82932": -1, "94493": -1, "49554": -1, "20288": 1.1}, "project_preferences": []}, {"_id": 98490, "name": "Christopher Jones", "attributes": {"1": [1], "7": [3, 4, 5], "6": [3], "100": [4]}, "relationships": {"-1": 1.1}, "project_preferences": []}, {"_id": 74992, "name": "Kristina Neal", "attributes": {"1": [1], "7": [3], "6": [3], "100": [3]}, "relationships": {"55821": -1, "60617": -1, "83807": -1, "96034": 1.1}, "project_preferences": []}]}, {"_id": 9, "name": "Team 9", "project_id": null, "requirements": [], "students": [{"_id": 31496, "name": "John Collins", "attributes": {"1": [1], "7": [2, 4, 5, 6], "6": [3], "100": [3]}, "relationships": {"19992": -1, "31496": -1, "-1": 1.1}, "project_preferences": []}, {"_id": 56561, "name": "Mark Cook", "attributes": {"1": [1], "7": [2, 3, 4, 5, 6], "6": [3], "100": [2]}, "relationships": {"-1": 1.1}, "project_preferences": []}, {"_id": 96820, "name": "Allison Brock", "attributes": {"1": [1], "7": [2, 5, 6], "6": [3], "100": [3]}, "relationships": {"64558": -1, "46278": -1, "62437": -1, "-1": 1.1}, "project_preferences": []}, {"_id": 25315, "name": "Douglas Harrington", "attributes": {"1": [1], "7": [1, 2], "6": [3], "100": [4]}, "relationships": {"37147": -1, "52521": -1, "61306": -1, "65317": 1.1}, "project_preferences": []}]}, {"_id": 10, "name": "Team 10", "project_id": null, "requirements": [], "students": [{"_id": 23276, "name": "Christina Vargas", "attributes": {"1": [1], "7": [3, 4, 5, 6], "6": [3], "100": [3]}, "relationships": {"-1": 1.1}, "project_preferences": []}, {"_id": 91855, "name": "Gabriel Vincent", "attributes": {"1": [1], "7": [4, 5, 6], "6": [3], "100": [4]}, "relationships": {"16300": -1, "27161": -1, "44120": -1, "-1": 1.1}, "project_preferences": []}, {"_id": 65876, "name": "Andrea Mullins", "attributes": {"1": [1], "7": [4, 5], "6": [3], "100": [3]}, "relationships": {"-1": -1, "21965": 1.1}, "project_preferences": []}, {"_id": 46706, "name": "Rebecca Davis", "attributes": {"1": [1], "7": [4, 5], "6": [3], "100": [3]}, "relationships": {"-1": 1.1}, "project_preferences": []}]}, {"_id": 11, "name": "Team 11", "project_id": null, "requirements": [], "students": [{"_id": 25658, "name": "Dylan Mcdaniel", "attributes": {"1": [2], "7": [2, 5, 6], "6": [3], "100": [3]}, "relationships": {"25658": 1.1, "79441": -1}, "project_preferences": []}, {"_id": 73799, "name": "Heather Guzman", "attributes": {"1": [2], "7": [2, 5], "6": [3], "100": [3]}, "relationships": {"76597": -1, "-1": 1.1}, "project_preferences": []}, {"_id": 30061, "name": "Daniel Murphy", "attributes": {"1": [1], "7": [6], "6": [3], "100": [4]}, "relationships": {"-1": -1, "24534": 1.1}, "project_preferences": []}, {"_id": 79441, "name": "Jeremy Tucker", "attributes": {"1": [2], "7": [1, 5, 6], "6": [3], "100": [4]}, "relationships": {"23512": -1, "69426": -1, "37147": -1, "94493": 1.1}, "project_preferences": []}]}, {"_id": 12, "name": "Team 12", "project_id": null, "requirements": [], "students": [{"_id": 83807, "name": "Chad Shaw", "attributes": {"1": [1], "7": [1, 2, 5, 6], "6": [3], "100": [3]}, "relationships": {"-1": 1.1}, "project_preferences": []}, {"_id": 24176, "name": "Richard Mccoy", "attributes": {"1": [1], "7": [5, 6], "6": [3], "100": [4]}, "relationships": {"94022": -1, "35088": -1, "55265": -1, "12284": 1.1}, "project_preferences": []}, {"_id": 48755, "name": "Robert Barrett", "attributes": {"1": [1], "7": [6], "6": [3], "100": [3]}, "relationships": {"67392": -1, "67618": -1, "78054": -1, "35088": 1.1}, "project_preferences": []}, {"_id": 78054, "name": "Brandi Mathews", "attributes": {"1": [1], "7": [3, 4, 5, 6], "6": [3], "100": [4]}, "relationships": {"67392": -1, "48755": -1, "79441": -1, "12284": 1.1}, "project_preferences": []}]}, {"_id": 13, "name": "Team 13", "project_id": null, "requirements": [], "students": [{"_id": 63773, "name": "Matthew Brown", "attributes": {"1": [1], "7": [3, 4, 5, 6], "6": [3], "100": [3]}, "relationships": {"62437": -1, "44120": -1, "46440": -1, "-1": 1.1}, "project_preferences": []}, {"_id": 19276, "name": "Sheila Nguyen", "attributes": {"1": [1], "7": [2, 3, 4, 5, 6], "6": [3], "100": [3]}, "relationships": {"20288": -1, "-1": -1, "68546": 1.1}, "project_preferences": []}, {"_id": 71923, "name": "Anthony Morgan", "attributes": {"1": [1], "7": [4, 5, 6], "6": [3], "100": [3]}, "relationships": {"86076": -1, "23512": -1, "53746": -1, "-1": 1.1}, "project_preferences": []}, {"_id": 12284, "name": "Jeffrey Young", "attributes": {"1": [1], "7": [2, 3, 4, 5], "6": [3], "100": [4]}, "relationships": {"56482": -1, "41039": -1, "22900": -1, "-1": 1.1}, "project_preferences": []}]}, {"_id": 14, "name": "Team 14", "project_id": null, "requirements": [], "students": [{"_id": 30600, "name": "Rachael Chung", "attributes": {"1": [1], "7": [3, 4, 5, 6], "6": [3], "100": [4]}, "relationships": {"21965": -1, "21484": -1, "52521": -1, "-1": 1.1}, "project_preferences": []}, {"_id": 55821, "name": "Christian Weaver", "attributes": {"1": [1], "7": [3, 4], "6": [3], "100": [4]}, "relationships": {"74992": -1, "60617": -1, "96034": -1, "17100": 1.1}, "project_preferences": []}, {"_id": 28511, "name": "Brittany Brown", "attributes": {"1": [1], "7": [1, 2, 5, 6], "6": [3], "100": [3]}, "relationships": {"-1": -1, "51805": 1.1}, "project_preferences": []}, {"_id": 83050, "name": "Thomas Li", "attributes": {"1": [1], "7": [1, 5, 6], "6": [3], "100": [4]}, "relationships": {"-1": 1.1}, "project_preferences": []}]}, {"_id": 15, "name": "Team 15", "project_id": null, "requirements": [], "students": [{"_id": 56482, "name": "Mr. David Patterson DDS", "attributes": {"1": [1], "7": [1, 2, 3, 5, 6], "6": [3], "100": [3]}, "relationships": {"41039": -1, "24176": -1, "12284": -1, "-1": 1.1}, "project_preferences": []}, {"_id": 21880, "name": "Joshua Hernandez", "attributes": {"1": [1], "7": [1, 2, 6], "6": [3], "100": [3]}, "relationships": {"-1": 1.1}, "project_preferences": []}, {"_id": 93660, "name": "Sara Sutton", "attributes": {"1": [1], "7": [2, 3, 4], "6": [3], "100": [4]}, "relationships": {"-1": -1, "28183": 1.1}, "project_preferences": []}, {"_id": 42745, "name": "Lawrence Rodriguez", "attributes": {"1": [1], "7": [2, 3, 6], "6": [3], "100": [3]}, "relationships": {"-1": 1.1}, "project_preferences": []}]}, {"_id": 16, "name": "Team 16", "project_id": null, "requirements": [], "students": [{"_id": 28844, "name": "James Velasquez", "attributes": {"1": [1], "7": [1, 5, 6], "6": [3], "100": [3]}, "relationships": {"12529": -1, "71974": -1, "-1": 1.1}, "project_preferences": []}, {"_id": 96160, "name": "Timothy Gonzalez", "attributes": {"1": [1], "7": [4, 5, 6], "6": [3], "100": [4]}, "relationships": {"-1": 1.1}, "project_preferences": []}, {"_id": 95915, "name": "Kimberly Garza", "attributes": {"1": [1], "7": [2, 5], "6": [3], "100": [3]}, "relationships": {"79489": -1, "36218": -1, "-1": 1.1}, "project_preferences": []}, {"_id": 70402, "name": "William Mendez", "attributes": {"1": [1], "7": [2, 4, 5], "6": [3], "100": [3]}, "relationships": {"18680": -1, "-1": 1.1}, "project_preferences": []}]}, {"_id": 17, "name": "Team 17", "project_id": null, "requirements": [], "students": [{"_id": 21001, "name": "Casey Griffith", "attributes": {"1": [1], "7": [2, 3, 4, 5], "6": [3], "100": [3]}, "relationships": {"-1": 1.1}, "project_preferences": []}, {"_id": 31637, "name": "Matthew Jackson", "attributes": {"1": [1], "7": [2, 3, 5], "6": [3], "100": [4]}, "relationships": {"-1": 1.1}, "project_preferences": []}, {"_id": 44120, "name": "Karen Stevens", "attributes": {"1": [1], "7": [2, 3, 4, 5], "6": [3], "100": [4]}, "relationships": {"62437": -1, "46440": -1, "63773": -1, "-1": 1.1}, "project_preferences": []}, {"_id": 17972, "name": "Victor Crawford", "attributes": {"1": [1], "7": [2, 3, 4, 5], "6": [3], "100": [3]}, "relationships": {"-1": 1.1}, "project_preferences": []}]}, {"_id": 18, "name": "Team 18", "project_id": null, "requirements": [], "students": [{"_id": 53746, "name": "Lacey Wolf", "attributes": {"1": [1], "7": [1, 2, 6], "6": [3], "100": [2]}, "relationships": {"71923": -1, "44120": -1, "81962": -1, "-1": 1.1}, "project_preferences": []}, {"_id": 15231, "name": "Joseph Gray", "attributes": {"1": [1], "7": [1, 2, 6], "6": [3], "100": [4]}, "relationships": {"29434": -1, "66724": -1, "67618": -1, "47504": 1.1}, "project_preferences": []}, {"_id": 80037, "name": "Emily Johnston", "attributes": {"1": [1], "7": [3, 4, 5, 6], "6": [3], "100": [3]}, "relationships": {"-1": 1.1}, "project_preferences": []}, {"_id": 46278, "name": "James Leblanc", "attributes": {"1": [1], "7": [2, 3, 4, 5, 6], "6": [3], "100": [3]}, "relationships": {"64558": -1, "96820": -1, "62437": -1, "-1": 1.1}, "project_preferences": []}]}, {"_id": 19, "name": "Team 19", "project_id": null, "requirements": [], "students": [{"_id": 79426, "name": "Jose Lane", "attributes": {"1": [2], "7": [5, 6], "6": [3], "100": [3]}, "relationships": {"32896": -1, "-1": -1, "95915": 1.1}, "project_preferences": []}, {"_id": 28183, "name": "Molly Fox", "attributes": {"1": [2], "7": [], "6": [3], "100": [4]}, "relationships": {"93660": -1, "-1": 1.1}, "project_preferences": []}, {"_id": 77506, "name": "Tommy Taylor", "attributes": {"1": [2], "7": [5], "6": [3], "100": [2]}, "relationships": {"65204": -1, "57350": -1, "-1": 1.1}, "project_preferences": []}, {"_id": 33244, "name": "Kelli Schwartz", "attributes": {"1": [2], "7": [3, 4, 5, 6], "6": [3], "100": [4]}, "relationships": {"-1": 1.1}, "project_preferences": []}]}, {"_id": 20, "name": "Team 20", "project_id": null, "requirements": [], "students": [{"_id": 38447, "name": "Mrs. Michelle Barry", "attributes": {"1": [1], "7": [3, 4, 5], "6": [3], "100": [3]}, "relationships": {"66724": -1, "-1": 1.1}, "project_preferences": []}, {"_id": 46273, "name": "Pamela Medina", "attributes": {"1": [1], "7": [3, 4, 5], "6": [3], "100": [3]}, "relationships": {"-1": 1.1}, "project_preferences": []}, {"_id": 10757, "name": "Cheryl Chandler", "attributes": {"1": [1], "7": [2, 3, 4, 5], "6": [3], "100": [3]}, "relationships": {"-1": 1.1}, "project_preferences": []}, {"_id": 71974, "name": "Sandy Garcia", "attributes": {"1": [1], "7": [3, 4, 5], "6": [3], "100": [4]}, "relationships": {"-1": 1.1}, "project_preferences": []}]}, {"_id": 21, "name": "Team 21", "project_id": null, "requirements": [], "students": [{"_id": 55265, "name": "Richard Blake", "attributes": {"1": [1], "7": [5, 6], "6": [3], "100": [3]}, "relationships": {"94022": -1, "24176": -1, "35088": -1, "-1": 1.1}, "project_preferences": []}, {"_id": 50058, "name": "Kevin Galvan", "attributes": {"1": [1], "7": [2, 5, 6], "6": [3], "100": [3]}, "relationships": {"70402": -1, "-1": -1, "21880": 1.1}, "project_preferences": []}, {"_id": 45608, "name": "Brandi Olson", "attributes": {"1": [1], "7": [5, 6], "6": [3], "100": [3]}, "relationships": {"-1": 1.1}, "project_preferences": []}, {"_id": 67392, "name": "Alexis Roberts", "attributes": {"1": [1], "7": [3, 5, 6], "6": [3], "100": [3]}, "relationships": {"78054": -1, "48755": -1, "24176": -1, "-1": 1.1}, "project_preferences": []}]}, {"_id": 22, "name": "Team 22", "project_id": null, "requirements": [], "students": [{"_id": 61306, "name": "Robert Adams", "attributes": {"1": [2], "7": [3, 4], "6": [3], "100": [4]}, "relationships": {"52521": -1, "37147": -1, "-1": 1.1}, "project_preferences": []}, {"_id": 30259, "name": "Lisa Sullivan", "attributes": {"1": [2], "7": [4, 5], "6": [3], "100": [4]}, "relationships": {"-1": 1.1}, "project_preferences": []}, {"_id": 55381, "name": "Jennifer Cisneros", "attributes": {"1": [1], "7": [4, 5, 6], "6": [3], "100": [3]}, "relationships": {"44120": -1, "-1": 1.1}, "project_preferences": []}, {"_id": 98023, "name": "Amber Livingston", "attributes": {"1": [1], "7": [3, 4], "6": [3], "100": [4]}, "relationships": {"-1": 1.1}, "project_preferences": []}]}, {"_id": 23, "name": "Team 23", "project_id": null, "requirements": [], "students": [{"_id": 14577, "name": "Steven Jenkins", "attributes": {"1": [1], "7": [2, 3, 4], "6": [3], "100": [4]}, "relationships": {"-1": 1.1}, "project_preferences": []}, {"_id": 86313, "name": "John Valenzuela", "attributes": {"1": [1], "7": [2, 3, 4], "6": [3], "100": [3]}, "relationships": {"-1": 1.1}, "project_preferences": []}, {"_id": 30296, "name": "Kevin Cannon", "attributes": {"1": [1], "7": [2, 3, 4, 5, 6], "6": [3], "100": [4]}, "relationships": {"45301": -1, "90716": -1, "86076": -1, "-1": 1.1}, "project_preferences": []}, {"_id": 24907, "name": "Martin Peters", "attributes": {"1": [1], "7": [1, 2, 3, 4], "6": [3], "100": [4]}, "relationships": {"78917": -1, "35088": -1, "43485": -1, "-1": 1.1}, "project_preferences": []}]}, {"_id": 24, "name": "Team 24", "project_id": null, "requirements": [], "students": [{"_id": 21656, "name": "Kathy Lane", "attributes": {"1": [1], "7": [2, 3, 4, 5, 6], "6": [3], "100": [3]}, "relationships": {"98490": -1, "12529": -1, "88835": -1, "-1": 1.1}, "project_preferences": []}, {"_id": 29434, "name": "James Ramirez", "attributes": {"1": [1], "7": [2, 3, 4, 5, 6], "6": [3], "100": [4]}, "relationships": {"15231": -1, "94022": -1, "67618": -1, "65317": 1.1}, "project_preferences": []}, {"_id": 27161, "name": "Benjamin Martin", "attributes": {"1": [1], "7": [2, 4, 5, 6], "6": [3], "100": [3]}, "relationships": {"91855": -1, "29434": -1, "21965": -1, "-1": 1.1}, "project_preferences": []}, {"_id": 61805, "name": "Kevin Rowe", "attributes": {"1": [1], "7": [2, 3], "6": [5], "100": [4]}, "relationships": {"-1": 1.1}, "project_preferences": []}]}, {"_id": 25, "name": "Team 25", "project_id": null, "requirements": [], "students": [{"_id": 28906, "name": "Carolyn Gordon", "attributes": {"1": [1], "7": [3, 4, 5, 6], "6": [3], "100": [3]}, "relationships": {"38192": -1, "83050": -1, "-1": 1.1}, "project_preferences": []}, {"_id": 64558, "name": "Christopher Contreras", "attributes": {"1": [1], "7": [2, 3, 4, 5], "6": [3], "100": [3]}, "relationships": {"96820": -1, "46278": -1, "-1": 1.1}, "project_preferences": []}, {"_id": 23512, "name": "Mark Khan", "attributes": {"1": [1], "7": [2, 3, 4, 5], "6": [3], "100": [3]}, "relationships": {"79441": -1, "-1": 1.1}, "project_preferences": []}, {"_id": 67618, "name": "Timothy Mitchell", "attributes": {"1": [1], "7": [2, 3, 5, 6], "6": [3], "100": [3]}, "relationships": {"24176": -1, "67392": -1, "48755": -1, "28996": 1.1}, "project_preferences": []}]}, {"_id": 26, "name": "Team 26", "project_id": null, "requirements": [], "students": [{"_id": 80449, "name": "Timothy Mason", "attributes": {"1": [2], "7": [2, 4, 5], "6": [3], "100": [4]}, "relationships": {"-1": 1.1}, "project_preferences": []}, {"_id": 14980, "name": "Taylor Rodriguez", "attributes": {"1": [2], "7": [2, 3, 4], "6": [5], "100": [4]}, "relationships": {"61805": -1, "97216": -1, "51547": -1, "67155": 1.1}, "project_preferences": []}, {"_id": 29471, "name": "Yvonne Pearson", "attributes": {"1": [2], "7": [2, 3, 4, 5], "6": [3], "100": [4]}, "relationships": {"21965": -1, "24996": -1, "-1": -1, "71066": 1.1}, "project_preferences": []}, {"_id": 47504, "name": "Ashley Hodges", "attributes": {"1": [2], "7": [2, 3, 4, 6], "6": [3], "100": [3]}, "relationships": {"29471": -1, "57350": -1, "16256": -1, "-1": 1.1}, "project_preferences": []}]}, {"_id": 27, "name": "Team 27", "project_id": null, "requirements": [], "students": [{"_id": 14038, "name": "Brenda Griffith", "attributes": {"1": [1], "7": [4], "6": [3], "100": [3]}, "relationships": {"94022": -1, "16300": -1, "12529": -1, "25315": 1.1}, "project_preferences": []}, {"_id": 43485, "name": "Matthew Wu", "attributes": {"1": [1], "7": [2, 4, 5], "6": [3], "100": [3]}, "relationships": {"96034": -1, "43485": -1, "60617": -1, "-1": 1.1}, "project_preferences": []}, {"_id": 96034, "name": "Katelyn Larson", "attributes": {"1": [1], "7": [4, 5], "6": [3], "100": [4]}, "relationships": {"43485": -1, "60617": -1, "74992": -1, "-1": 1.1}, "project_preferences": []}, {"_id": 85891, "name": "Donald Jarvis", "attributes": {"1": [1], "7": [4, 5], "6": [3], "100": [4]}, "relationships": {"-1": 1.1}, "project_preferences": []}]}, {"_id": 28, "name": "Team 28", "project_id": null, "requirements": [], "students": [{"_id": 42656, "name": "Frank Hart", "attributes": {"1": [1], "7": [5, 6], "6": [3], "100": [3]}, "relationships": {"87008": -1, "44924": -1, "19992": -1, "51547": 1.1}, "project_preferences": []}, {"_id": 68546, "name": "Paul Petersen", "attributes": {"1": [1], "7": [5], "6": [3], "100": [3]}, "relationships": {"52400": -1, "19276": -1, "53713": -1, "-1": 1.1}, "project_preferences": []}, {"_id": 79489, "name": "Mr. Drew Barnes", "attributes": {"1": [1], "7": [5], "6": [3], "100": [3]}, "relationships": {"36218": -1, "69426": -1, "-1": 1.1}, "project_preferences": []}, {"_id": 24534, "name": "Jason Leblanc", "attributes": {"1": [1], "7": [1, 5, 6], "6": [3], "100": [3]}, "relationships": {"-1": 1.1}, "project_preferences": []}]}, {"_id": 29, "name": "Team 29", "project_id": null, "requirements": [], "students": [{"_id": 29846, "name": "Zachary Williams", "attributes": {"1": [1], "7": [2, 5, 6], "6": [3], "100": [4]}, "relationships": {"79814": -1, "85726": -1, "22172": -1, "-1": 1.1}, "project_preferences": []}, {"_id": 94022, "name": "Rachel Wall", "attributes": {"1": [1], "7": [5, 6], "6": [3], "100": [3]}, "relationships": {"24176": -1, "35088": -1, "55265": -1, "31903": 1.1}, "project_preferences": []}, {"_id": 35088, "name": "Andrew Lowery", "attributes": {"1": [1], "7": [5, 6], "6": [3], "100": [4]}, "relationships": {"24176": -1, "94022": -1, "55265": -1, "-1": 1.1}, "project_preferences": []}, {"_id": 17905, "name": "Jason Hunter", "attributes": {"1": [1], "7": [5, 6], "6": [3], "100": [4]}, "relationships": {"-1": 1.1}, "project_preferences": []}]}, {"_id": 30, "name": "Team 30", "project_id": null, "requirements": [], "students": [{"_id": 50028, "name": "Scott Sanchez", "attributes": {"1": [1], "7": [5, 6], "6": [3], "100": [3]}, "relationships": {"-1": 1.1}, "project_preferences": []}, {"_id": 75481, "name": "Justin Cunningham", "attributes": {"1": [1], "7": [5, 6], "6": [5], "100": [4]}, "relationships": {"51547": -1, "54788": -1, "32278": -1, "-1": 1.1}, "project_preferences": []}, {"_id": 60617, "name": "Christine Alvarez", "attributes": {"1": [1], "7": [4, 5, 6], "6": [3], "100": [4]}, "relationships": {"96034": -1, "74992": -1, "55821": -1, "44924": 1.1}, "project_preferences": []}, {"_id": 19252, "name": "Joshua Rice", "attributes": {"1": [1], "7": [5], "6": [3], "100": [3]}, "relationships": {"76597": -1, "-1": 1.1}, "project_preferences": []}]}, {"_id": 31, "name": "Team 31", "project_id": null, "requirements": [], "students": [{"_id": 94976, "name": "Kim Glover", "attributes": {"1": [1], "7": [1, 6], "6": [3], "100": [2]}, "relationships": {"12076": -1, "52521": -1, "55362": -1, "49357": 1.1}, "project_preferences": []}, {"_id": 71066, "name": "Evan Haynes", "attributes": {"1": [1], "7": [2], "6": [3], "100": [4]}, "relationships": {"80449": -1, "29471": -1, "87008": -1, "30257": 1.1}, "project_preferences": []}, {"_id": 75940, "name": "Mr. Austin Roberts", "attributes": {"1": [5], "7": [1, 2], "6": [3], "100": [2]}, "relationships": {"-1": 1.1}, "project_preferences": []}, {"_id": 11916, "name": "Ana Thomas", "attributes": {"1": [1], "7": [2, 5], "6": [3], "100": [3]}, "relationships": {"-1": -1, "76416": 1.1}, "project_preferences": []}]}, {"_id": 32, "name": "Team 32", "project_id": null, "requirements": [], "students": [{"_id": 97587, "name": "Christine Maxwell", "attributes": {"1": [2], "7": [2, 3, 4, 5], "6": [3], "100": [3]}, "relationships": {"-1": -1, "45335": 1.1}, "project_preferences": []}, {"_id": 69426, "name": "Jessica Wilson", "attributes": {"1": [1], "7": [2, 3, 4, 5, 6], "6": [3], "100": [3]}, "relationships": {"79441": -1, "36218": -1, "79489": -1, "67392": 1.1}, "project_preferences": []}, {"_id": 18680, "name": "Michael Silva", "attributes": {"1": [1], "7": [3, 4], "6": [3], "100": [3]}, "relationships": {"70402": -1, "-1": 1.1}, "project_preferences": []}, {"_id": 65204, "name": "Gerald Lee", "attributes": {"1": [2], "7": [2, 3, 4], "6": [3], "100": [4]}, "relationships": {"-1": 1.1, "57350": -1}, "project_preferences": []}]}, {"_id": 33, "name": "Team 33", "project_id": null, "requirements": [], "students": [{"_id": 15269, "name": "Jennifer Morris", "attributes": {"1": [1], "7": [1, 4, 5, 6], "6": [3], "100": [3]}, "relationships": {"-1": 1.1}, "project_preferences": []}, {"_id": 12529, "name": "Jamie Mcdonald", "attributes": {"1": [1], "7": [2, 3, 6], "6": [3], "100": [4]}, "relationships": {"76597": -1, "32896": -1, "99819": -1, "65317": 1.1}, "project_preferences": []}, {"_id": 17100, "name": "Rhonda Padilla", "attributes": {"1": [1], "7": [1, 6], "6": [3], "100": [3]}, "relationships": {"31903": -1, "-1": 1.1}, "project_preferences": []}, {"_id": 62437, "name": "Brandi Hughes", "attributes": {"1": [1], "7": [1, 2, 3, 4, 5, 6], "6": [3], "100": [3]}, "relationships": {"63773": -1, "44120": -1, "46440": -1, "64558": 1.1}, "project_preferences": []}]}, {"_id": 34, "name": "Team 34", "project_id": null, "requirements": [], "students": [{"_id": 16300, "name": "Laura Rangel PhD", "attributes": {"1": [2], "7": [4, 5, 6], "6": [3], "100": [4]}, "relationships": {"-1": 1.1}, "project_preferences": []}, {"_id": 73050, "name": "Yvette Ford", "attributes": {"1": [1], "7": [4, 5, 6], "6": [3], "100": [4]}, "relationships": {"-1": 1.1}, "project_preferences": []}, {"_id": 16256, "name": "Katherine Williams", "attributes": {"1": [1], "7": [3, 4, 5, 6], "6": [3], "100": [4]}, "relationships": {"-1": 1.1}, "project_preferences": []}, {"_id": 13555, "name": "Nicole Johnson", "attributes": {"1": [1], "7": [4, 5, 6], "6": [3], "100": [4]}, "relationships": {"97216": -1, "-1": 1.1}, "project_preferences": []}]}, {"_id": 35, "name": "Team 35", "project_id": null, "requirements": [], "students": [{"_id": 99819, "name": "Jonathan Santiago", "attributes": {"1": [1], "7": [1, 2, 3, 4, 5, 6], "6": [3], "100": [4]}, "relationships": {"65317": -1, "60617": -1, "51805": -1, "24907": 1.1}, "project_preferences": []}, {"_id": 52635, "name": "Mackenzie Stewart", "attributes": {"1": [1], "7": [2, 3, 4, 5, 6], "6": [3], "100": [4]}, "relationships": {"-1": 1.1}, "project_preferences": []}, {"_id": 12076, "name": "Natalie King", "attributes": {"1": [1], "7": [1, 2, 3, 4, 5, 6], "6": [3], "100": [4]}, "relationships": {"22172": -1, "-1": 1.1}, "project_preferences": []}, {"_id": 76416, "name": "Tabitha Barnett", "attributes": {"1": [1], "7": [3, 4, 5, 6], "6": [3], "100": [3]}, "relationships": {"12529": -1, "67618": -1, "21490": -1, "47504": 1.1}, "project_preferences": []}]}, {"_id": 36, "name": "Team 36", "project_id": null, "requirements": [], "students": [{"_id": 36218, "name": "Elizabeth Martin", "attributes": {"1": [1], "7": [3, 4, 5, 6], "6": [3], "100": [4]}, "relationships": {"69426": -1, "79489": -1, "-1": 1.1}, "project_preferences": []}, {"_id": 41039, "name": "Ashley Moore", "attributes": {"1": [1], "7": [2, 4, 5, 6], "6": [3], "100": [3]}, "relationships": {"12284": -1, "56482": -1, "-1": 1.1}, "project_preferences": []}, {"_id": 37147, "name": "Duane Rogers", "attributes": {"1": [1], "7": [2, 5, 6], "6": [3], "100": [4]}, "relationships": {"52521": -1, "61306": -1, "25315": -1, "-1": 1.1}, "project_preferences": []}, {"_id": 31903, "name": "Ronald Farmer", "attributes": {"1": [1], "7": [2, 3, 4, 5, 6], "6": [3], "100": [3]}, "relationships": {"-1": 1.1}, "project_preferences": []}]}, {"_id": 37, "name": "Team 37", "project_id": null, "requirements": [], "students": [{"_id": 91694, "name": "Jordan Gilbert", "attributes": {"1": [2], "7": [1, 2, 5, 6], "6": [5], "100": [3]}, "relationships": {"-1": 1.1}, "project_preferences": []}, {"_id": 38192, "name": "Kimberly Navarro", "attributes": {"1": [1], "7": [1, 2, 5, 6], "6": [3], "100": [3]}, "relationships": {"28906": -1, "-1": 1.1}, "project_preferences": []}, {"_id": 59390, "name": "Amy Jackson", "attributes": {"1": [2], "7": [1], "6": [5], "100": [1]}, "relationships": {"43485": -1, "73596": -1, "56201": -1, "-1": 1.1}, "project_preferences": []}, {"_id": 97216, "name": "David Thomas", "attributes": {"1": [2], "7": [2, 4], "6": [5], "100": [4]}, "relationships": {"76597": -1, "13555": -1, "67155": -1, "-1": 1.1}, "project_preferences": []}]}, {"_id": 38, "name": "Team 38", "project_id": null, "requirements": [], "students": [{"_id": 78917, "name": "Cameron Wilson", "attributes": {"1": [1], "7": [3, 4, 5], "6": [3], "100": [3]}, "relationships": {"24907": -1, "43485": -1, "94022": -1, "49357": 1.1}, "project_preferences": []}, {"_id": 70758, "name": "Holly Medina", "attributes": {"1": [1], "7": [], "6": [3], "100": [3]}, "relationships": {"90716": -1, "35088": -1, "73471": -1, "32896": 1.1}, "project_preferences": []}, {"_id": 36463, "name": "Rachel Mitchell", "attributes": {"1": [1], "7": [4, 5], "6": [3], "100": [4]}, "relationships": {"-1": 1.1}, "project_preferences": []}, {"_id": 59459, "name": "Sarah Clark", "attributes": {"1": [1], "7": [3, 4, 5, 6], "6": [3], "100": [4]}, "relationships": {"-1": 1.1}, "project_preferences": []}]}, {"_id": 39, "name": "Team 39", "project_id": null, "requirements": [], "students": [{"_id": 67767, "name": "Zoe Lee", "attributes": {"1": [1], "7": [2, 4, 5], "6": [3], "100": [3]}, "relationships": {"-1": -1, "71923": 1.1}, "project_preferences": []}, {"_id": 38069, "name": "Carolyn Davis", "attributes": {"1": [1], "7": [4, 5], "6": [3], "100": [3]}, "relationships": {"45301": -1, "30296": -1, "47504": -1, "55362": 1.1}, "project_preferences": []}, {"_id": 85726, "name": "Linda Poole", "attributes": {"1": [1], "7": [4, 5, 6], "6": [3], "100": [4]}, "relationships": {"79814": -1, "22172": -1, "29846": -1, "86613": 1.1}, "project_preferences": []}, {"_id": 24996, "name": "John Hodge", "attributes": {"1": [1], "7": [1, 5, 6], "6": [3], "100": [4]}, "relationships": {"28996": -1, "21965": -1, "33998": -1, "-1": 1.1}, "project_preferences": []}]}, {"_id": 40, "name": "Team 40", "project_id": null, "requirements": [], "students": [{"_id": 32416, "name": "Kyle Thompson", "attributes": {"1": [2], "7": [3, 4, 5], "6": [3], "100": [3]}, "relationships": {"-1": 1.1}, "project_preferences": []}, {"_id": 20288, "name": "Lori Murphy", "attributes": {"1": [2], "7": [3, 4, 5], "6": [3], "100": [3]}, "relationships": {"20288": -1, "19992": -1, "19276": -1, "68546": 1.1}, "project_preferences": []}, {"_id": 15189, "name": "Mr. Todd Thomas DDS", "attributes": {"1": [2], "7": [2, 3, 4, 5], "6": [3], "100": [4]}, "relationships": {"64558": -1, "-1": 1.1}, "project_preferences": []}, {"_id": 44924, "name": "April Weaver", "attributes": {"1": [2], "7": [5], "6": [3], "100": [3]}, "relationships": {"-1": 1.1}, "project_preferences": []}]}, {"_id": 41, "name": "Team 41", "project_id": null, "requirements": [], "students": [{"_id": 33998, "name": "Denise Flores", "attributes": {"1": [1], "7": [2, 3, 5, 6], "6": [3], "100": [3]}, "relationships": {"-1": 1.1}, "project_preferences": []}, {"_id": 19142, "name": "Sarah Huff", "attributes": {"1": [1], "7": [2, 3, 5], "6": [3], "100": [3]}, "relationships": {"-1": 1.1}, "project_preferences": []}, {"_id": 94493, "name": "Monica Smith", "attributes": {"1": [1], "7": [2, 3, 6], "6": [3], "100": [4]}, "relationships": {"49639": -1, "70758": -1, "-1": 1.1}, "project_preferences": []}, {"_id": 28996, "name": "John Medina", "attributes": {"1": [1], "7": [2, 3, 5], "6": [3], "100": [3]}, "relationships": {"-1": -1, "67618": 1.1}, "project_preferences": []}]}, {"_id": 42, "name": "Team 42", "project_id": null, "requirements": [], "students": [{"_id": 86076, "name": "Meghan Thornton", "attributes": {"1": [1], "7": [4, 6], "6": [3], "100": [3]}, "relationships": {"-1": 1.1}, "project_preferences": []}, {"_id": 66724, "name": "Brett Cole DDS", "attributes": {"1": [1], "7": [3, 5, 6], "6": [3], "100": [4]}, "relationships": {"38447": -1, "15231": -1, "94022": -1, "-1": 1.1}, "project_preferences": []}, {"_id": 49639, "name": "Michelle Moore", "attributes": {"1": [1], "7": [3, 4, 5], "6": [3], "100": [3]}, "relationships": {"94493": -1, "12529": -1, "18680": -1, "86313": 1.1}, "project_preferences": []}, {"_id": 98433, "name": "Michael Wells", "attributes": {"1": [1], "7": [2, 3, 4, 5], "6": [3], "100": [4]}, "relationships": {"-1": 1.1}, "project_preferences": []}]}, {"_id": 43, "name": "Team 43", "project_id": null, "requirements": [], "students": [{"_id": 97884, "name": "John Walter", "attributes": {"1": [1], "7": [2, 5, 6], "6": [3], "100": [4]}, "relationships": {"-1": 1.1}, "project_preferences": []}, {"_id": 57350, "name": "Sheila Dixon", "attributes": {"1": [1], "7": [2, 5, 6], "6": [3], "100": [3]}, "relationships": {"65204": -1, "-1": 1.1}, "project_preferences": []}, {"_id": 10981, "name": "Nathan Vasquez", "attributes": {"1": [1], "7": [1, 2, 5, 6], "6": [3], "100": [4]}, "relationships": {"-1": 1.1}, "project_preferences": []}, {"_id": 49554, "name": "Casey Braun", "attributes": {"1": [1], "7": [1, 5, 6], "6": [3], "100": [4]}, "relationships": {"31637": -1, "12529": -1, "31903": -1, "38069": 1.1}, "project_preferences": []}]}, {"_id": 44, "name": "Team 44", "project_id": null, "requirements": [], "students": [{"_id": 67155, "name": "David Parker", "attributes": {"1": [2], "7": [2, 3, 4, 5], "6": [5], "100": [3]}, "relationships": {"-1": 1.1}, "project_preferences": []}, {"_id": 81573, "name": "Wesley Gomez", "attributes": {"1": [2], "7": [1, 2, 3, 4], "6": [3], "100": [4]}, "relationships": {"-1": 1.1}, "project_preferences": []}, {"_id": 76597, "name": "Olivia Kelley", "attributes": {"1": [2], "7": [1, 3, 5, 6], "6": [3], "100": [4]}, "relationships": {"12529": -1, "97216": -1, "32896": -1, "21965": 1.1}, "project_preferences": []}]}]}], "runtimes": [1784.9517812728882]}